Workbook

Sheet Sales Log
A1: ARCHIVE-35 — Sales & Tax Tracker
A2: Log every sale here. Formulas calculate your tax obligations automatically.
A4: TAX ASSUMPTIONS | D4: BLUE = Input cells you edit | BLACK = Formulas (don't touch)
A5: CA Sales Tax Rate: | B5: 0.095 | D5: Adjust tax rates in B5:B10 if needed. These are conservative estimates. Your actual rates depend on total household income with Lucy's physician salary.
A6: Federal SE Tax Rate: | B6: 0.153
A7: Fed Income Tax Rate: | B7: 0.24
A8: CA State Income Tax: | B8: 0.093
A9: Stripe Fee Rate: | B9: 0.029
A10: Stripe Per-Transaction: | B10: 0.3
A12: Date | B12: Order # | C12: Product Description | D12: Customer State/Country | E12: Sale Price | F12: Pictorem Cost | G12: Stripe Fees | H12: Sales Tax Collected | I12: Net Revenue | J12: Your Profit | K12: Tax Reserve (Set Aside) | L12: Cumulative Profit | M12: Cumulative Tax Reserve
G13: =IF(E13="","",E13*$B$9+$B$10) | H13: =IF(E13="","",IF(OR(D13="CA",D13="California"),E13*$B$5,0)) | I13: =IF(E13="","",E13-F13-G13) | J13: =IF(E13="","",I13) | K13: =IF(E13="","",J13*($B$6+$B$7+$B$8)+H13) | L13: =IF(E13="","",J13) | M13: =IF(E13="","",K13)
G14: =IF(E14="","",E14*$B$9+$B$10) | H14: =IF(E14="","",IF(OR(D14="CA",D14="California"),E14*$B$5,0)) | I14: =IF(E14="","",E14-F14-G14) | J14: =IF(E14="","",I14) | K14: =IF(E14="","",J14*($B$6+$B$7+$B$8)+H14) | L14: =IF(E14="","",L13+J14) | M14: =IF(E14="","",M13+K14)
G15: =IF(E15="","",E15*$B$9+$B$10) | H15: =IF(E15="","",IF(OR(D15="CA",D15="California"),E15*$B$5,0)) | I15: =IF(E15="","",E15-F15-G15) | J15: =IF(E15="","",I15) | K15: =IF(E15="","",J15*($B$6+$B$7+$B$8)+H15) | L15: =IF(E15="","",L14+J15) | M15: =IF(E15="","",M14+K15)
G16: =IF(E16="","",E16*$B$9+$B$10) | H16: =IF(E16="","",IF(OR(D16="CA",D16="California"),E16*$B$5,0)) | I16: =IF(E16="","",E16-F16-G16) | J16: =IF(E16="","",I16) | K16: =IF(E16="","",J16*($B$6+$B$7+$B$8)+H16) | L16: =IF(E16="","",L15+J16) | M16: =IF(E16="","",M15+K16)
G17: =IF(E17="","",E17*$B$9+$B$10) | H17: =IF(E17="","",IF(OR(D17="CA",D17="California"),E17*$B$5,0)) | I17: =IF(E17="","",E17-F17-G17) | J17: =IF(E17="","",I17) | K17: =IF(E17="","",J17*($B$6+$B$7+$B$8)+H17) | L17: =IF(E17="","",L16+J17) | M17: =IF(E17="","",M16+K17)
G18: =IF(E18="","",E18*$B$9+$B$10) | H18: =IF(E18="","",IF(OR(D18="CA",D18="California"),E18*$B$5,0)) | I18: =IF(E18="","",E18-F18-G18) | J18: =IF(E18="","",I18) | K18: =IF(E18="","",J18*($B$6+$B$7+$B$8)+H18) | L18: =IF(E18="","",L17+J18) | M18: =IF(E18="","",M17+K18)
G19: =IF(E19="","",E19*$B$9+$B$10) | H19: =IF(E19="","",IF(OR(D19="CA",D19="California"),E19*$B$5,0)) | I19: =IF(E19="","",E19-F19-G19) | J19: =IF(E19="","",I19) | K19: =IF(E19="","",J19*($B$6+$B$7+$B$8)+H19) | L19: =IF(E19="","",L18+J19) | M19: =IF(E19="","",M18+K19)
G20: =IF(E20="","",E20*$B$9+$B$10) | H20: =IF(E20="","",IF(OR(D20="CA",D20="California"),E20*$B$5,0)) | I20: =IF(E20="","",E20-F20-G20) | J20: =IF(E20="","",I20) | K20: =IF(E20="","",J20*($B$6+$B$7+$B$8)+H20) | L20: =IF(E20="","",L19+J20) | M20: =IF(E20="","",M19+K20)
G21: =IF(E21="","",E21*$B$9+$B$10) | H21: =IF(E21="","",IF(OR(D21="CA",D21="California"),E21*$B$5,0)) | I21: =IF(E21="","",E21-F21-G21) | J21: =IF(E21="","",I21) | K21: =IF(E21="","",J21*($B$6+$B$7+$B$8)+H21) | L21: =IF(E21="","",L20+J21) | M21: =IF(E21="","",M20+K21)
G22: =IF(E22="","",E22*$B$9+$B$10) | H22: =IF(E22="","",IF(OR(D22="CA",D22="California"),E22*$B$5,0)) | I22: =IF(E22="","",E22-F22-G22) | J22: =IF(E22="","",I22) | K22: =IF(E22="","",J22*($B$6+$B$7+$B$8)+H22) | L22: =IF(E22="","",L21+J22) | M22: =IF(E22="","",M21+K22)
G23: =IF(E23="","",E23*$B$9+$B$10) | H23: =IF(E23="","",IF(OR(D23="CA",D23="California"),E23*$B$5,0)) | I23: =IF(E23="","",E23-F23-G23) | J23: =IF(E23="","",I23) | K23: =IF(E23="","",J23*($B$6+$B$7+$B$8)+H23) | L23: =IF(E23="","",L22+J23) | M23: =IF(E23="","",M22+K23)
G24: =IF(E24="","",E24*$B$9+$B$10) | H24: =IF(E24="","",IF(OR(D24="CA",D24="California"),E24*$B$5,0)) | I24: =IF(E24="","",E24-F24-G24) | J24: =IF(E24="","",I24) | K24: =IF(E24="","",J24*($B$6+$B$7+$B$8)+H24) | L24: =IF(E24="","",L23+J24) | M24: =IF(E24="","",M23+K24)
G25: =IF(E25="","",E25*$B$9+$B$10) | H25: =IF(E25="","",IF(OR(D25="CA",D25="California"),E25*$B$5,0)) | I25: =IF(E25="","",E25-F25-G25) | J25: =IF(E25="","",I25) | K25: =IF(E25="","",J25*($B$6+$B$7+$B$8)+H25) | L25: =IF(E25="","",L24+J25) | M25: =IF(E25="","",M24+K25)
... G112: =IF(E112="","",E112*$B$9+$B$10) | H112: =IF(E112="","",IF(OR(D112="CA",D112="California"),E112*$B$5,0)) | I112: =IF(E112="","",E112-F112-G112) | J112: =IF(E112="","",I112) | K112: =IF(E112="","",J112*($B$6+$B$7+$B$8)+H112) | L112: =IF(E112="","",L111+J112) | M112: =IF(E112="","",M111+K112)
A113: TOTALS | E113: =SUM(E13:E112) -> 0 | F113: =SUM(F13:F112) -> 0 | G113: =SUM(G13:G112) -> 0 | H113: =SUM(H13:H112) -> 0 | I113: =SUM(I13:I112) -> 0 | J113: =SUM(J13:J112) -> 0 | K113: =SUM(K13:K112) -> 0

Sheet Expenses
A1: ARCHIVE-35 — Business Expenses (Schedule C Deductions)
A2: Track ALL business expenses here. These reduce your taxable profit on Schedule C.
A4: Date | B4: Description | C4: Category | D4: Amount | E4: Payment Method | F4: Receipt? | G4: Notes
A5: Categories: Pictorem (COGS) | Stripe Fees | Website/Hosting | Software | Equipment | Home Office | Marketing | Supplies | Travel | Filing Fees | Insurance | Other
A106: TOTAL EXPENSES | D106: =SUM(D6:D105) -> 0
A108: EXPENSE SUMMARY BY CATEGORY
A109: Pictorem (COGS) | B109: =SUMIF(C6:C105,A109,D6:D105) -> 0
A110: Stripe Fees | B110: =SUMIF(C6:C105,A110,D6:D105) -> 0
A111: Website/Hosting | B111: =SUMIF(C6:C105,A111,D6:D105) -> 0
A112: Software | B112: =SUMIF(C6:C105,A112,D6:D105) -> 0
A113: Equipment | B113: =SUMIF(C6:C105,A113,D6:D105) -> 0
A114: Home Office | B114: =SUMIF(C6:C105,A114,D6:D105) -> 0
A115: Marketing | B115: =SUMIF(C6:C105,A115,D6:D105) -> 0
A116: Supplies | B116: =SUMIF(C6:C105,A116,D6:D105) -> 0
A117: Travel | B117: =SUMIF(C6:C105,A117,D6:D105) -> 0
A118: Filing Fees | B118: =SUMIF(C6:C105,A118,D6:D105) -> 0
A119: Insurance | B119: =SUMIF(C6:C105,A119,D6:D105) -> 0
A120: Other | B120: =SUMIF(C6:C105,A120,D6:D105) -> 0

Sheet Quarterly Summary
A1: ARCHIVE-35 — Quarterly Tax Summary & Payment Tracker
A2: Use this to calculate quarterly estimated tax payments. Lucy files quarterly — add Archive-35 amounts to her payments.
B4: Q1 Jan-Mar | C4: Q2 Apr-Jun | D4: Q3 Jul-Sep | E4: Q4 Oct-Dec | F4: YTD Total
A5: Gross Sales | F5: =SUM(B5:E5) -> 0
A6: Pictorem Costs (COGS) | F6: =SUM(B6:E6) -> 0
A7: Stripe Fees | F7: =SUM(B7:E7) -> 0
A8: Other Business Expenses | F8: =SUM(B8:E8) -> 0
A9: Total Expenses | B9: =B6+B7+B8 -> 0 | C9: =C6+C7+C8 -> 0 | D9: =D6+D7+D8 -> 0 | E9: =E6+E7+E8 -> 0 | F9: =SUM(B9:E9) -> 0
A11: NET PROFIT (Loss) | B11: =B5-B9 -> 0 | C11: =C5-C9 -> 0 | D11: =D5-D9 -> 0 | E11: =E5-E9 -> 0 | F11: =SUM(B11:E11) -> 0
A13: TAX OBLIGATIONS:
A14: Sales Tax Collected (remit to CDTFA) | F14: =SUM(B14:E14) -> 0
A15: Self-Employment Tax (15.3%) | B15: =IF(B11>0,B11*'Sales Log'!$B$6,0) -> 0 | C15: =IF(C11>0,C11*'Sales Log'!$B$6,0) -> 0 | D15: =IF(D11>0,D11*'Sales Log'!$B$6,0) -> 0 | E15: =IF(E11>0,E11*'Sales Log'!$B$6,0) -> 0 | F15: =SUM(B15:E15) -> 0
A16: Federal Income Tax (~24%) | B16: =IF(B11>0,B11*'Sales Log'!$B$7,0) -> 0 | C16: =IF(C11>0,C11*'Sales Log'!$B$7,0) -> 0 | D16: =IF(D11>0,D11*'Sales Log'!$B$7,0) -> 0 | E16: =IF(E11>0,E11*'Sales Log'!$B$7,0) -> 0 | F16: =SUM(B16:E16) -> 0
A17: CA State Income Tax (~9.3%) | B17: =IF(B11>0,B11*'Sales Log'!$B$8,0) -> 0 | C17: =IF(C11>0,C11*'Sales Log'!$B$8,0) -> 0 | D17: =IF(D11>0,D11*'Sales Log'!$B$8,0) -> 0 | E17: =IF(E11>0,E11*'Sales Log'!$B$8,0) -> 0 | F17: =SUM(B17:E17) -> 0
A18: Total Tax Due This Quarter | B18: =B14+B15+B16+B17 -> 0 | C18: =C14+C15+C16+C17 -> 0 | D18: =D14+D15+D16+D17 -> 0 | E18: =E14+E15+E16+E17 -> 0 | F18: =SUM(B18:E18) -> 0
A20: PAYMENT TRACKING:
A21: Fed Estimated Payment Made | F21: =SUM(B21:E21) -> 0
A22: CA Estimated Payment Made | F22: =SUM(B22:E22) -> 0
A23: CDTFA Sales Tax Payment Made | F23: =SUM(B23:E23) -> 0
A24: Total Payments Made | B24: =B21+B22+B23 -> 0 | C24: =C21+C22+C23 -> 0 | D24: =D21+D22+D23 -> 0 | E24: =E21+E22+E23 -> 0 | F24: =SUM(B24:E24) -> 0
A26: BALANCE (owed or overpaid) | B26: =B24-B18 -> 0 | C26: =C24-C18 -> 0 | D26: =D24-D18 -> 0 | E26: =E24-E18 -> 0 | F26: =SUM(B26:E26) -> 0
A28: QUARTERLY PAYMENT DUE DATES:
A29: Q1: April 15, 2026
A30: Q2: June 15, 2026
A31: Q3: September 15, 2026
A32: Q4: January 15, 2027

Sheet EDD Reporting
A1: ARCHIVE-35 — EDD Bi-Weekly Income Reporting
A2: Report GROSS income (before expenses) to EDD every 2 weeks. This is separate from your tax calculations.
A3: ⚠️ EDD counts GROSS revenue, not net profit. Report the full sale price, not what you keep after costs.
A4: Weekly Benefit Amount: | B4: 450
A5: Cert Period Start | B5: Cert Period End | C5: Gross Revenue (Archive-35) | D5: EDD Weekly Benefit | E5: Earnings Disregard (25%) | F5: Benefit After Reduction
D6: =$B$4 -> 450 | E6: =D6*0.25 -> 112.5 | F6: =IF(C6="",D6,MAX(0,D6-(C6-E6))) -> 450
D7: =$B$4 -> 450 | E7: =D7*0.25 -> 112.5 | F7: =IF(C7="",D7,MAX(0,D7-(C7-E7))) -> 450
D8: =$B$4 -> 450 | E8: =D8*0.25 -> 112.5 | F8: =IF(C8="",D8,MAX(0,D8-(C8-E8))) -> 450
D9: =$B$4 -> 450 | E9: =D9*0.25 -> 112.5 | F9: =IF(C9="",D9,MAX(0,D9-(C9-E9))) -> 450
D10: =$B$4 -> 450 | E10: =D10*0.25 -> 112.5 | F10: =IF(C10="",D10,MAX(0,D10-(C10-E10))) -> 450
D11: =$B$4 -> 450 | E11: =D11*0.25 -> 112.5 | F11: =IF(C11="",D11,MAX(0,D11-(C11-E11))) -> 450
D12: =$B$4 -> 450 | E12: =D12*0.25 -> 112.5 | F12: =IF(C12="",D12,MAX(0,D12-(C12-E12))) -> 450
D13: =$B$4 -> 450 | E13: =D13*0.25 -> 112.5 | F13: =IF(C13="",D13,MAX(0,D13-(C13-E13))) -> 450
D14: =$B$4 -> 450 | E14: =D14*0.25 -> 112.5 | F14: =IF(C14="",D14,MAX(0,D14-(C14-E14))) -> 450
D15: =$B$4 -> 450 | E15: =D15*0.25 -> 112.5 | F15: =IF(C15="",D15,MAX(0,D15-(C15-E15))) -> 450
D16: =$B$4 -> 450 | E16: =D16*0.25 -> 112.5 | F16: =IF(C16="",D16,MAX(0,D16-(C16-E16))) -> 450
D17: =$B$4 -> 450 | E17: =D17*0.25 -> 112.5 | F17: =IF(C17="",D17,MAX(0,D17-(C17-E17))) -> 450
... D31: =$B$4 -> 450 | E31: =D31*0.25 -> 112.5 | F31: =IF(C31="",D31,MAX(0,D31-(C31-E31))) -> 450
